public final class i
  implements Runnable
{
  public i(q paramq) {}
  
  /* Error */
  public final void run()
  {
    // Byte code:
    //   0: ldc 38
    //   2: invokestatic 15	q:a	(Ljava/lang/String;)V
    //   5: invokestatic 20	q:c	()I
    //   8: tableswitch	default:+367->375, 0:+24->32, 1:+24->32
    //   32: aconst_null
    //   33: astore_1
    //   34: ldc 41
    //   36: invokestatic 15	q:a	(Ljava/lang/String;)V
    //   39: invokestatic 21	q:d	()Ljava/lang/String;
    //   42: astore 7
    //   44: aconst_null
    //   45: astore 6
    //   47: aconst_null
    //   48: astore 8
    //   50: new 129	XConnection
    //   53: dup
    //   54: invokespecial 131	XConnection:<init>	()V
    //   57: astore 9
    //   59: aload 7
    //   61: ldc -123
    //   63: invokevirtual 137	java/lang/String:startsWith	(Ljava/lang/String;)Z
    //   66: ifeq +10 -> 76
    //   69: aload 9
    //   71: astore 8
    //   73: goto +10 -> 83
    //   76: aload 7
    //   78: invokestatic 139	javax/microedition/io/Connector:open	(Ljava/lang/String;)Ljavax/microedition/io/Connection;
    //   81: astore 8
    //   83: aload 8
    //   85: checkcast 10	javax/wireless/messaging/MessageConnection
    //   88: astore_1
    //   89: iconst_2
    //   90: invokestatic 16	q:a	(I)V
    //   93: ldc 40
    //   95: invokestatic 15	q:a	(Ljava/lang/String;)V
    //   98: invokestatic 20	q:c	()I
    //   101: ifne +76 -> 177
    //   104: aload_1
    //   105: ldc 46
    //   107: astore 7
    //   109: astore 6
    //   111: aconst_null
    //   112: astore 8
    //   114: new 141	XMessage
    //   117: dup
    //   118: invokespecial 143	XMessage:<init>	()V
    //   121: astore 8
    //   123: aload 8
    //   125: nop
    //   126: nop
    //   127: nop
    //   128: checkcast 11	javax/wireless/messaging/TextMessage
    //   131: dup
    //   132: astore_2
    //   133: invokestatic 22	q:e	()Ljava/lang/String;
    //   136: invokeinterface 31 2 0
    //   141: ldc 34
    //   143: invokestatic 15	q:a	(Ljava/lang/String;)V
    //   146: iconst_3
    //   147: invokestatic 16	q:a	(I)V
    //   150: ldc 39
    //   152: invokestatic 15	q:a	(Ljava/lang/String;)V
    //   155: aload_1
    //   156: aload_2
    //   157: astore 7
    //   159: astore 6
    //   161: getstatic 149	java/lang/System:out	Ljava/io/PrintStream;
    //   164: ldc -105
    //   166: invokevirtual 156	java/io/PrintStream:println	(Ljava/lang/String;)V
    //   169: nop
    //   170: iconst_4
    //   171: invokestatic 16	q:a	(I)V
    //   174: goto +175 -> 349
    //   177: invokestatic 20	q:c	()I
    //   180: iconst_1
    //   181: if_icmpne +168 -> 349
    //   184: aload_1
    //   185: ldc 45
    //   187: astore 7
    //   189: astore 6
    //   191: aconst_null
    //   192: astore 8
    //   194: new 141	XMessage
    //   197: dup
    //   198: invokespecial 158	XMessage:<init>	()V
    //   201: astore 8
    //   203: aload 8
    //   205: nop
    //   206: nop
    //   207: nop
    //   208: checkcast 9	javax/wireless/messaging/BinaryMessage
    //   211: dup
    //   212: astore_2
    //   213: invokestatic 22	q:e	()Ljava/lang/String;
    //   216: invokevirtual 24	java/lang/String:getBytes	()[B
    //   219: invokeinterface 30 2 0
    //   224: ldc 34
    //   226: invokestatic 15	q:a	(Ljava/lang/String;)V
    //   229: iconst_3
    //   230: invokestatic 16	q:a	(I)V
    //   233: ldc 39
    //   235: invokestatic 15	q:a	(Ljava/lang/String;)V
    //   238: aload_1
    //   239: aload_2
    //   240: astore 7
    //   242: astore 6
    //   244: getstatic 160	java/lang/System:out	Ljava/io/PrintStream;
    //   247: ldc -95
    //   249: invokevirtual 163	java/io/PrintStream:println	(Ljava/lang/String;)V
    //   252: nop
    //   253: iconst_4
    //   254: invokestatic 16	q:a	(I)V
    //   257: goto +92 -> 349
    //   260: astore_2
    //   261: iconst_5
    //   262: invokestatic 16	q:a	(I)V
    //   265: new 6	java/lang/StringBuffer
    //   268: dup
    //   269: ldc 32
    //   271: invokespecial 14	java/lang/StringBuffer:<init>	(Ljava/lang/String;)V
    //   274: invokestatic 23	q:f	()I
    //   277: invokevirtual 17	java/lang/StringBuffer:append	(I)Ljava/lang/StringBuffer;
    //   280: ldc 44
    //   282: invokevirtual 18	java/lang/StringBuffer:append	(Ljava/lang/String;)Ljava/lang/StringBuffer;
    //   285: invokevirtual 26	java/lang/StringBuffer:toString	()Ljava/lang/String;
    //   288: invokestatic 15	q:a	(Ljava/lang/String;)V
    //   291: new 6	java/lang/StringBuffer
    //   294: dup
    //   295: ldc 33
    //   297: invokespecial 14	java/lang/StringBuffer:<init>	(Ljava/lang/String;)V
    //   300: aload_2
    //   301: invokevirtual 19	java/lang/StringBuffer:append	(Ljava/lang/Object;)Ljava/lang/StringBuffer;
    //   304: ldc 44
    //   306: invokevirtual 18	java/lang/StringBuffer:append	(Ljava/lang/String;)Ljava/lang/StringBuffer;
    //   309: invokevirtual 26	java/lang/StringBuffer:toString	()Ljava/lang/String;
    //   312: invokestatic 15	q:a	(Ljava/lang/String;)V
    //   315: goto +34 -> 349
    //   318: astore 4
    //   320: aload_1
    //   321: ifnull +25 -> 346
    //   324: aload_1
    //   325: astore 6
    //   327: aload 6
    //   329: aconst_null
    //   330: if_acmpeq +10 -> 340
    //   333: aload 6
    //   335: invokeinterface 165 1 0
    //   340: nop
    //   341: nop
    //   342: goto +4 -> 346
    //   345: pop
    //   346: aload 4
    //   348: athrow
    //   349: aload_1
    //   350: ifnull +25 -> 375
    //   353: aload_1
    //   354: astore 6
    //   356: aload 6
    //   358: aconst_null
    //   359: if_acmpeq +10 -> 369
    //   362: aload 6
    //   364: invokeinterface 167 1 0
    //   369: nop
    //   370: nop
    //   371: goto +4 -> 375
    //   374: pop
    //   375: invokestatic 23	q:f	()I
    //   378: ifle +82 -> 460
    //   381: invokestatic 23	q:f	()I
    //   384: tableswitch	default:+71->455, 1:+32->416, 2:+43->427, 3:+54->438, 4:+65->449
    //   416: bipush -5
    //   418: invokestatic 16	q:a	(I)V
    //   421: ldc 43
    //   423: invokestatic 15	q:a	(Ljava/lang/String;)V
    //   426: return
    //   427: bipush -6
    //   429: invokestatic 16	q:a	(I)V
    //   432: ldc 42
    //   434: invokestatic 15	q:a	(Ljava/lang/String;)V
    //   437: return
    //   438: bipush -7
    //   440: invokestatic 16	q:a	(I)V
    //   443: ldc 35
    //   445: invokestatic 15	q:a	(Ljava/lang/String;)V
    //   448: return
    //   449: ldc 37
    //   451: invokestatic 15	q:a	(Ljava/lang/String;)V
    //   454: return
    //   455: ldc 36
    //   457: invokestatic 15	q:a	(Ljava/lang/String;)V
    //   460: return
    // Local variable table:
    //   start	length	slot	name	signature
    //   0	461	0	this	i
    //   33	321	1	localMessageConnection1	javax.wireless.messaging.MessageConnection
    //   132	108	2	localObject1	Object
    //   260	41	2	localException1	Exception
    //   318	29	4	localObject2	Object
    //   45	318	6	localMessageConnection2	javax.wireless.messaging.MessageConnection
    //   42	199	7	localObject3	Object
    //   48	156	8	localObject4	Object
    //   57	13	9	localXConnection	XConnection
    //   345	1	9	localException2	Exception
    //   374	1	10	localException3	Exception
    // Exception table:
    //   from	to	target	type
    //   34	260	260	java/lang/Exception
    //   34	318	318	finally
    //   324	345	345	java/lang/Exception
    //   353	374	374	java/lang/Exception
  }
}


/* Location:              D:\Coding\Coding_JAVA\JavaGame\game_source.jar!\i.class
 * Java compiler version: 1 (45.3)
 * JD-Core Version:       0.7.1
 */